pyquil_for_azure_quantum/__init__.py
pyquil_for_azure_quantum/py.typed
pyquil_for_azure_quantum-0.1.0.dist-info/LICENSE
pyquil_for_azure_quantum-0.1.0.dist-info/METADATA
pyquil_for_azure_quantum-0.1.0.dist-info/WHEEL
pyquil_for_azure_quantum-0.1.0.dist-info/RECORD
