Metadata-Version: 2.3
Name: pyquil-for-azure-quantum
Version: 0.1.0
Summary: Run Quil programs on Microsoft Azure Quantum using pyQuil
License: Apache-2.0
Author: Dylan Anthony
Author-email: danthony@rigetti.com
Requires-Python: >=3.9,<3.13
Classifier: Development Status :: 3 - Alpha
Classifier: Intended Audience :: Science/Research
Classifier: License :: OSI Approved :: Apache Software License
Classifier: Programming Language :: Python :: 3
Classifier: Programming Language :: Python :: 3.9
Classifier: Programming Language :: Python :: 3.10
Classifier: Programming Language :: Python :: 3.11
Classifier: Programming Language :: Python :: 3.12
Classifier: Topic :: Scientific/Engineering
Classifier: Typing :: Typed
Requires-Dist: aiohttp (>=3.10.10)
Requires-Dist: azure-quantum (>=0.27,<1.0)
Requires-Dist: lazy-object-proxy (>=1.7.1,<2.0.0)
Requires-Dist: multidict (>=6.0.5)
Requires-Dist: numpy (>=1.21.6,<2.0.0)
Requires-Dist: pyquil (>=4.14.3,<5.0.0)
Requires-Dist: qcs-sdk-python (==0.20.1)
Requires-Dist: scipy (>=1.6.1,<2.0.0)
Requires-Dist: wrapt (>=1.14.0,<2.0.0)
Project-URL: Documentation, https://rigetti.github.io/pyquil-for-azure-quantum/
Project-URL: Repository, https://github.com/rigetti/pyquil-for-azure-quantum
